MANIFEST.in
README.txt
setup.py
mathinfinity/__init__.py
mathinfinity/arithmeticoperation.py
mathinfinity/checkdivisibilityseriesrange.py
mathinfinity/checkdivisibilityseriesrangearray.py
mathinfinity/checkevenodd.py
mathinfinity/checkevenoddseriesrange.py
mathinfinity/checkevenoddseriesrangearray.py
mathinfinity/divisibility.py
mathinfinity/divisionoperation.py
mathinfinity/posnegzero.py
mathinfinity/printrange.py
mathinfinity/printzerorange.py
mathinfinity.egg-info/PKG-INFO
mathinfinity.egg-info/SOURCES.txt
mathinfinity.egg-info/dependency_links.txt
mathinfinity.egg-info/top_level.txt