Metadata-Version: 2.4
Name: mathinfinity
Version: 0.0.15
Summary: mathinfinity Python Package Is For All Types Of Mathematical Solutions.
Home-page: 
Author: ATISH KUMAR SAHU
Author-email: kumarsahuatishoff280301@gmail.com
License: MIT
Keywords: mathinfinity,arithmetic operations,addition,subtraction,multiplication,division,modulo
Classifier: Development Status :: 3 - Alpha
Classifier: Intended Audience :: Education
Classifier: Intended Audience :: Developers
Classifier: Programming Language :: Python :: 3
Classifier: Programming Language :: Python :: 3.10
Classifier: Programming Language :: Python :: 3.11
Classifier: Programming Language :: Python :: 3.12
Classifier: Programming Language :: Python :: 3.13
Classifier: Operating System :: OS Independent
Dynamic: author
Dynamic: author-email
Dynamic: classifier
Dynamic: description
Dynamic: description-content-type
Dynamic: keywords
Dynamic: license
Dynamic: summary
